[
  {
    "name": "001_guduyuchensi_Sul·plvdm",
    "file": "001_guduyuchensi_Sul·plvdm.md"
  },
  {
    "name": "002_Romeshi_TeAoder·mSen",
    "file": "002_Romeshi_TeAoder·mSen.md"
  },
  {
    "name": "003_tiaozhan'sshouCollection_bynscheNa·bangsong",
    "file": "003_tiaozhan'sshouCollection_bynscheNa·bangsong.md"
  },
  {
    "name": "004_HuangjIsland_Frederick·msTeLaer",
    "file": "004_HuangjIsland_Frederick·msTeLaer.md"
  },
  {
    "name": "005_Great'sPullXianp_hes·aqJialai",
    "file": "005_Great'sPullXianp_hes·aqJialai.md"
  },
  {
    "name": "006_niwanghechuqu_HenryKe·xianKewzhi",
    "file": "006_niwanghechuqu_HenryKe·xianKewzhi.md"
  },
  {
    "name": "007_qingchun'sshi_Joezua·KarlDuq",
    "file": "007_qingchun'sshi_Joezua·KarlDuq.md"
  },
  {
    "name": "008_jm_Joseph·ldeyde·jbul",
    "file": "008_jm_Joseph·ldeyde·jbul.md"
  },
  {
    "name": "009_Greatsixiangj'spshengTemple_lderov·oKen",
    "file": "009_Greatsixiangj'spshengTemple_lderov·oKen.md"
  },
  {
    "name": "010_Nielsqielvxingji_serma·Laglov",
    "file": "010_Nielsqielvxingji_serma·Laglov.md"
  },
  {
    "name": "011_TeRaybiguniang_Paul·Seaze",
    "file": "011_TeRaybiguniang_Paul·Seaze.md"
  },
  {
    "name": "012_hua'szhihui_mLis·mTelKe",
    "file": "012_hua'szhihui_mLis·mTelKe.md"
  },
  {
    "name": "013_qmo_gerHaTe·hopTeMan",
    "file": "013_qmo_gerHaTe·hopTeMan.md"
  },
  {
    "name": "014_jpsyaoquji_LabdeLaNaTe·tger",
    "file": "014_jpsyaoquji_LabdeLaNaTe·tger.md"
  },
  {
    "name": "015_John·Kelsduoov_LuoMan·Luol",
    "file": "015_John·Kelsduoov_LuoMan·Luol.md"
  },
  {
    "name": "016_chaoSaintYeardai_weierNa·von·SeadsTowerm",
    "file": "016_chaoSaintYeardai_weierNa·von·SeadsTowerm.md"
  },
  {
    "name": "017_ligshang'sshuguang_Karl·Adov·jLelp",
    "file": "017_ligshang'sshuguang_Karl·Adov·jLelp.md"
  },
  {
    "name": "018_youlhaiguanDepartment'syiyuan_HenryKe·pengtpdan",
    "file": "018_youlhaiguanDepartment'syiyuan_HenryKe·pengtpdan.md"
  },
  {
    "name": "019_Aolby'schunt_Karl·spTeLe",
    "file": "019_Aolby'schunt_Karl·spTeLe.md"
  },
  {
    "name": "020_kewang_KenTe·hmsheng",
    "file": "020_kewang_KenTe·hmsheng.md"
  },
  {
    "name": "021_geiqingYearship'sxin_ANater·flangs",
    "file": "021_geiqingYearship'sxin_ANater·flangs.md"
  },
  {
    "name": "022_dyuLi'sdongt_Haxt·bNawTe",
    "file": "022_dyuLi'sdongt_Haxt·bNawTe.md"
  },
  {
    "name": "023_lidyute_W-B-Yeats",
    "file": "023_lidyute_W-B-Yeats.md"
  },
  {
    "name": "024_Dad_fLadsLaov·lmTe",
    "file": "024_Dad_fLadsLaov·lmTe.md"
  },
  {
    "name": "025_Saintfzhende_George·xiaobNa",
    "file": "025_Saintfzhende_George·xiaobNa.md"
  },
  {
    "name": "026_xieezhil_gLaqy·daild",
    "file": "026_xieezhil_gLaqy·daild.md"
  },
  {
    "name": "027_weiniersi_Henry·baigSen",
    "file": "027_weiniersi_Henry·baigSen.md"
  },
  {
    "name": "028_War_xgLide·wsTe",
    "file": "028_War_xgLide·wsTe.md"
  },
  {
    "name": "029_meiyoutud'spmen_Thomas·Man",
    "file": "029_meiyoutud'spmen_Thomas·Man.md"
  },
  {
    "name": "030_bbTe_xKel·liuys",
    "file": "030_bbTe_xKel·liuys.md"
  },
  {
    "name": "031_youchanzhe_aLiKe·Karlferde",
    "file": "031_youchanzhe_aLiKe·Karlferde.md"
  },
  {
    "name": "032_huangyuanlang_Johannes·William·yanSen",
    "file": "032_huangyuanlang_Johannes·William·yanSen.md"
  },
  {
    "name": "033_tianySymphony_Yifan·ylKeswq·pun",
    "file": "033_tianySymphony_Yifan·ylKeswq·pun.md"
  },
  {
    "name": "034_xunzhaoziwo_Louisj·pldelou",
    "file": "034_xunzhaoziwo_Louisj·pldelou.md"
  },
  {
    "name": "035_bushimeiyouxiao_Eugene·Aoner",
    "file": "035_bushimeiyouxiao_Eugene·Aoner.md"
  },
  {
    "name": "036_qiadyov_Roger·Martin·DuJiaer",
    "file": "036_qiadyov_Roger·Martin·DuJiaer.md"
  },
  {
    "name": "037_Dadshang'sjxiang_szhenzhu",
    "file": "037_Dadshang'sjxiang_szhenzhu.md"
  },
  {
    "name": "038_AlexanderQuartet_Frans-Emil-Sillanpaa",
    "file": "038_AlexanderQuartet_Frans-Emil-Sillanpaa.md"
  },
  {
    "name": "039_manChang'slvxing_Johannes·werSeam·yangSen",
    "file": "039_manChang'slvxing_Johannes·werSeam·yangSen.md"
  },
  {
    "name": "040_tianyshiqing_JiaovlLa·msTeLaer",
    "file": "040_tianyshiqing_JiaovlLa·msTeLaer.md"
  },
  {
    "name": "041_yuwangzhihua_Hermann·Heis",
    "file": "041_yuwangzhihua_Hermann·Heis.md"
  },
  {
    "name": "042_Anna·sj_Andre·jide",
    "file": "042_Anna·sj_Andre·jide.md"
  },
  {
    "name": "043_xuanhuayusaodong_T-S-Eliot",
    "file": "043_xuanhuayusaodong_T-S-Eliot.md"
  },
  {
    "name": "044_xiangqi'sStory_William·fKeNa",
    "file": "044_xiangqi'sStory_William·fKeNa.md"
  },
  {
    "name": "045_dyu1ji_bTel·Russell",
    "file": "045_dyu1ji_bTel·Russell.md"
  },
  {
    "name": "046_Bureauwaip_Aerb·Jiamiu",
    "file": "046_Bureauwaip_Aerb·Jiamiu.md"
  },
  {
    "name": "047_dengdaigd_Samuel·bKeTe",
    "file": "047_dengdaigd_Samuel·bKeTe.md"
  },
  {
    "name": "048_One-Hundred-Years_Jiaovler·Garcia-Marquez",
    "file": "048_One-Hundred-Years_Jiaovler·Garcia-Marquez.md"
  },
  {
    "name": "049_laopyuSea_Ernest·SeaMingw",
    "file": "049_laopyuSea_Ernest·SeaMingw.md"
  },
  {
    "name": "050_xueCountry_Kawabata-Yasunari",
    "file": "050_xueCountry_Kawabata-Yasunari.md"
  },
  {
    "name": "051_TiepDrum_junTe·gLas",
    "file": "051_TiepDrum_junTe·gLas.md"
  },
  {
    "name": "052_wo'smingzijiaoHong_Aoerhan·pmuKe",
    "file": "052_wo'smingzijiaoHong_Aoerhan·pmuKe.md"
  },
  {
    "name": "053_taoli_alisi·mLuo",
    "file": "053_taoli_alisi·mLuo.md"
  },
  {
    "name": "054_wa_Mo-Yan",
    "file": "054_wa_Mo-Yan.md"
  },
  {
    "name": "055_holuanPeriod'saiqing_Jiaovler·Garcia-Marquez",
    "file": "055_holuanPeriod'saiqing_Jiaovler·Garcia-Marquez.md"
  },
  {
    "name": "056_kanbujian'sCityCity_YiTowerl·Karlwn",
    "file": "056_kanbujian'sCityCity_YiTowerl·Karlwn.md"
  },
  {
    "name": "057_Norway'sForest_Villageshangchunshu",
    "file": "057_Norway'sForest_Villageshangchunshu.md"
  },
  {
    "name": "058_beicansjie_wKed·Hugo",
    "file": "058_beicansjie_wKed·Hugo.md"
  },
  {
    "name": "059_War-and-Peace_lov·Tolstoy",
    "file": "059_War-and-Peace_lov·Tolstoy.md"
  },
  {
    "name": "060_zuiyufa_Dostoevsky",
    "file": "060_zuiyufa_Dostoevsky.md"
  },
  {
    "name": "061_KaLamzuoovxiongdi_Dostoevsky",
    "file": "061_KaLamzuoovxiongdi_Dostoevsky.md"
  },
  {
    "name": "062_youlxs_James·JoeYis",
    "file": "062_youlxs_James·JoeYis.md"
  },
  {
    "name": "063_zhuiyisishuiYearh_mser·plsTe",
    "file": "063_zhuiyisishuiYearh_mser·plsTe.md"
  },
  {
    "name": "064_bianxingji_flc·KaovKa",
    "file": "064_bianxingji_flc·KaovKa.md"
  },
  {
    "name": "065_mtianLi'sshouwangzhe_JayLuom·slg",
    "file": "065_mtianLi'sshouwangzhe_JayLuom·slg.md"
  },
  {
    "name": "066_Great-Gatsby_F-Scott-Fitzgerald",
    "file": "066_Great-Gatsby_F-Scott-Fitzgerald.md"
  },
  {
    "name": "067_piao_magliTe·mqer",
    "file": "067_piao_magliTe·mqer.md"
  },
  {
    "name": "068_Little-Prince_Antwan·de·Saint-aKeSupLi",
    "file": "068_Little-Prince_Antwan·de·Saint-aKeSupLi.md"
  },
  {
    "name": "069_Hal·bTe_J.K.Luolin",
    "file": "069_Hal·bTe_J.K.Luolin.md"
  },
  {
    "name": "070_One-Hundred-Years_Jiaovler·Garcia-Marquez",
    "file": "070_One-Hundred-Years_Jiaovler·Garcia-Marquez.md"
  },
  {
    "name": "071_chonger_tni·mLiSen",
    "file": "071_chonger_tni·mLiSen.md"
  },
  {
    "name": "072_jsebiji_dlisi·lx",
    "file": "072_jsebiji_dlisi·lx.md"
  },
  {
    "name": "073_Xinpvavabing_S-Alexievich",
    "file": "073_Xinpvavabing_S-Alexievich.md"
  },
  {
    "name": "074_2shouHourjian_S-Alexievich",
    "file": "074_2shouHourjian_S-Alexievich.md"
  },
  {
    "name": "075_Cancerbingfang_Alexander·soerrennqin",
    "file": "075_Cancerbingfang_Alexander·soerrennqin.md"
  },
  {
    "name": "076_Daywgysheng_baoLis·psjieerNaKe",
    "file": "076_Daywgysheng_baoLis·psjieerNaKe.md"
  },
  {
    "name": "077_jingjing'sdRiver_mHaYier·xiaolhoov",
    "file": "077_jingjing'sdRiver_mHaYier·xiaolhoov.md"
  },
  {
    "name": "078_MasterhemagliTe_mHaYier·berJiaKeov",
    "file": "078_MasterhemagliTe_mHaYier·berJiaKeov.md"
  },
  {
    "name": "079_shengmingZhongbunengchengshouzhiqing_Milan·kundeLa",
    "file": "079_shengmingZhongbunengchengshouzhiqing_Milan·kundeLa.md"
  },
  {
    "name": "080_1984_George-Orwell",
    "file": "080_1984_George-Orwell.md"
  },
  {
    "name": "081_AnimalnongField_George-Orwell",
    "file": "081_AnimalnongField_George-Orwell.md"
  },
  {
    "name": "082_lliTower_fLajmer·NabKeov",
    "file": "082_lliTower_fLajmer·NabKeov.md"
  },
  {
    "name": "083_qingp_magliTe·DuLas",
    "file": "083_qingp_magliTe·DuLas.md"
  },
  {
    "name": "084_niHao，youchou_flsowsi·sgang",
    "file": "084_niHao，youchou_flsowsi·sgang.md"
  },
  {
    "name": "085_xiangshui_Patrick·jusjde",
    "file": "085_xiangshui_Patrick·jusjde.md"
  },
  {
    "name": "086_Suf'ssjie_Joest·jiade",
    "file": "086_Suf'ssjie_Joest·jiade.md"
  },
  {
    "name": "087_muyangShaoYearqhuanzhilv_Paul·Kealue",
    "file": "087_muyangShaoYearqhuanzhilv_Paul·Kealue.md"
  },
  {
    "name": "088_jingThornniao_kaolin·mKal",
    "file": "088_jingThornniao_kaolin·mKal.md"
  },
  {
    "name": "089_langBridgeyimeng_Robert·James·wLe",
    "file": "089_langBridgeyimeng_Robert·James·wLe.md"
  },
  {
    "name": "090_da-Vincimim_dan·bl",
    "file": "090_da-Vincimim_dan·bl.md"
  },
  {
    "name": "091_Harry-Potteryumofs_J.K.Luolin",
    "file": "091_Harry-Potteryumofs_J.K.Luolin.md"
  },
  {
    "name": "092_Twilight_Stephenni·mer",
    "file": "092_Twilight_Stephenni·mer.md"
  },
  {
    "name": "093_510duHui_E.L.James",
    "file": "093_510duHui_E.L.James.md"
  },
  {
    "name": "094_Three-Body_liucixin",
    "file": "094_Three-Body_liucixin.md"
  },
  {
    "name": "095_Beijingzhedie_haojingfang",
    "file": "095_Beijingzhedie_haojingfang.md"
  },
  {
    "name": "096_fanhua_jyucheng",
    "file": "096_fanhua_jyucheng.md"
  },
  {
    "name": "097_huozhe_Yu-Hua",
    "file": "097_huozhe_Yu-Hua.md"
  },
  {
    "name": "098_xu3Templemaixueji_Yu-Hua",
    "file": "098_xu3Templemaixueji_Yu-Hua.md"
  },
  {
    "name": "099_pingfan'ssjie_lyao",
    "file": "099_pingfan'ssjie_lyao.md"
  },
  {
    "name": "100_Bailuyuan_chenzhongshi",
    "file": "100_Bailuyuan_chenzhongshi.md"
  },
  {
    "name": "zonglan",
    "file": "zonglan.md"
  }
]