[
  {
    "name": "01_William·shasby",
    "file": "01_William·shasby.md"
  },
  {
    "name": "02_dand·AljyLi",
    "file": "02_dand·AljyLi.md"
  },
  {
    "name": "03_hem",
    "file": "03_hem.md"
  },
  {
    "name": "04_lov·Tolstoy",
    "file": "04_lov·Tolstoy.md"
  },
  {
    "name": "05_John·Wolfgang·von·gde",
    "file": "05_John·Wolfgang·von·gde.md"
  },
  {
    "name": "06_mger·de·swantis",
    "file": "06_mger·de·swantis.md"
  },
  {
    "name": "07_Zishibu",
    "file": "07_Zishibu.md"
  },
  {
    "name": "08_JayfLi·JoeElder",
    "file": "08_JayfLi·JoeElder.md"
  },
  {
    "name": "09_James·JoeYis",
    "file": "09_James·JoeYis.md"
  },
  {
    "name": "10_John·Milton",
    "file": "10_John·Milton.md"
  },
  {
    "name": "11_pblius·wjer·mLuo",
    "file": "11_pblius·wjer·mLuo.md"
  },
  {
    "name": "12_William·fKeNa",
    "file": "12_William·fKeNa.md"
  },
  {
    "name": "13_Alexander·phj",
    "file": "13_Alexander·phj.md"
  },
  {
    "name": "14_werTe·huiTeMan",
    "file": "14_werTe·huiTeMan.md"
  },
  {
    "name": "15_sitangd",
    "file": "15_sitangd.md"
  },
  {
    "name": "16_Ernest·SeaMingw",
    "file": "16_Ernest·SeaMingw.md"
  },
  {
    "name": "17_George·xiaobNa",
    "file": "17_George·xiaobNa.md"
  },
  {
    "name": "18_xlt·bolTe",
    "file": "18_xlt·bolTe.md"
  },
  {
    "name": "19_pox·bh·xuel",
    "file": "19_pox·bh·xuel.md"
  },
  {
    "name": "20_wKed·Hugo",
    "file": "20_wKed·Hugo.md"
  },
  {
    "name": "21_berzhaKe",
    "file": "21_berzhaKe.md"
  },
  {
    "name": "22_Charles·digengs",
    "file": "22_Charles·digengs.md"
  },
  {
    "name": "23_fAoder·Dostoevsky",
    "file": "23_fAoder·Dostoevsky.md"
  },
  {
    "name": "24_caoxueCelery",
    "file": "24_caoxueCelery.md"
  },
  {
    "name": "25_Dufu",
    "file": "25_Dufu.md"
  },
  {
    "name": "26_Lu-Xun",
    "file": "26_Lu-Xun.md"
  },
  {
    "name": "27_tger",
    "file": "27_tger.md"
  },
  {
    "name": "28_Kawabata-Yasunari",
    "file": "28_Kawabata-Yasunari.md"
  },
  {
    "name": "29_Jiaovler·Garcia-Marquez",
    "file": "29_Jiaovler·Garcia-Marquez.md"
  },
  {
    "name": "30_Mo-Yan",
    "file": "30_Mo-Yan.md"
  },
  {
    "name": "31_Gaoerj",
    "file": "31_Gaoerj.md"
  },
  {
    "name": "32_Mark·Spitw",
    "file": "32_Mark·Spitw.md"
  },
  {
    "name": "33_Francis·sKeTe·fcGerald",
    "file": "33_Francis·sKeTe·fcGerald.md"
  },
  {
    "name": "34_George-Orwell",
    "file": "34_George-Orwell.md"
  },
  {
    "name": "35_flz·KaovKa",
    "file": "35_flz·KaovKa.md"
  },
  {
    "name": "36_Aerb·Jiamiu",
    "file": "36_Aerb·Jiamiu.md"
  },
  {
    "name": "37_Jean-Paul·sTe",
    "file": "37_Jean-Paul·sTe.md"
  },
  {
    "name": "38_berhs",
    "file": "38_berhs.md"
  },
  {
    "name": "39_bboLuo·nield",
    "file": "39_bboLuo·nield.md"
  },
  {
    "name": "40_amli·bolTe",
    "file": "40_amli·bolTe.md"
  },
  {
    "name": "41_jian·Aosting",
    "file": "41_jian·Aosting.md"
  },
  {
    "name": "42_fjny·wuerov",
    "file": "42_fjny·wuerov.md"
  },
  {
    "name": "43_sofKeLes",
    "file": "43_sofKeLes.md"
  },
  {
    "name": "44_oLibides",
    "file": "44_oLibides.md"
  },
  {
    "name": "45_AListf",
    "file": "45_AListf.md"
  },
  {
    "name": "46_Aowde",
    "file": "46_Aowde.md"
  },
  {
    "name": "47_PeterLaKe",
    "file": "47_PeterLaKe.md"
  },
  {
    "name": "48_Bojiaqiu",
    "file": "48_Bojiaqiu.md"
  },
  {
    "name": "49_mLiai",
    "file": "49_mLiai.md"
  },
  {
    "name": "50_Lafengdan",
    "file": "50_Lafengdan.md"
  },
  {
    "name": "51_askLuos",
    "file": "51_askLuos.md"
  }
]