[
  {
    "name": "AdNa",
    "file": "AdNa.md"
  },
  {
    "name": "Alexander2s",
    "file": "Alexander2s.md"
  },
  {
    "name": "Benjamin·fulKel",
    "file": "Benjamin·fulKel.md"
  },
  {
    "name": "Brazillyqiandou",
    "file": "Brazillyqiandou.md"
  },
  {
    "name": "ChinaHdanshiyan",
    "file": "ChinaHdanshiyan.md"
  },
  {
    "name": "CountrygongFirstcihezuo",
    "file": "CountrygongFirstcihezuo.md"
  },
  {
    "name": "George·hshengd",
    "file": "George·hshengd.md"
  },
  {
    "name": "LeeDaZhao",
    "file": "LeeDaZhao.md"
  },
  {
    "name": "Leefuchun",
    "file": "Leefuchun.md"
  },
  {
    "name": "Martin·lde·j",
    "file": "Martin·lde·j.md"
  },
  {
    "name": "Nacuidangchengli",
    "file": "Nacuidangchengli.md"
  },
  {
    "name": "Richard·nKesong",
    "file": "Richard·nKesong.md"
  },
  {
    "name": "Searui",
    "file": "Searui.md"
  },
  {
    "name": "South-AfricafeiContinentpCountryminDahui",
    "file": "South-AfricafeiContinentpCountryminDahui.md"
  },
  {
    "name": "XinminzhuzhuyiTheory",
    "file": "XinminzhuzhuyiTheory.md"
  },
  {
    "name": "chentanqiu",
    "file": "chentanqiu.md"
  },
  {
    "name": "chenyi",
    "file": "chenyi.md"
  },
  {
    "name": "dengxpingfuchu",
    "file": "dengxpingfuchu.md"
  },
  {
    "name": "hlxiaoov",
    "file": "hlxiaoov.md"
  },
  {
    "name": "jiangjCountry",
    "file": "jiangjCountry.md"
  },
  {
    "name": "jiangjiesrenmengjuntongshuai",
    "file": "jiangjiesrenmengjuntongshuai.md"
  },
  {
    "name": "lKenyuci",
    "file": "lKenyuci.md"
  },
  {
    "name": "mCountryjinjling",
    "file": "mCountryjinjling.md"
  },
  {
    "name": "msTowerf·kmoer·ATowerterKe",
    "file": "msTowerf·kmoer·ATowerterKe.md"
  },
  {
    "name": "renAssistantHour",
    "file": "renAssistantHour.md"
  },
  {
    "name": "shenjunru",
    "file": "shenjunru.md"
  },
  {
    "name": "sunZhongMountain",
    "file": "sunZhongMountain.md"
  },
  {
    "name": "tshaoyi",
    "file": "tshaoyi.md"
  },
  {
    "name": "xingxingzhihuokeyiliaoyuan",
    "file": "xingxingzhihuokeyiliaoyuan.md"
  },
  {
    "name": "yejiany",
    "file": "yejiany.md"
  },
  {
    "name": "yuansk",
    "file": "yuansk.md"
  },
  {
    "name": "zhaoheth",
    "file": "zhaoheth.md"
  },
  {
    "name": "zhounlai",
    "file": "zhounlai.md"
  },
  {
    "name": "zunyihuiyi",
    "file": "zunyihuiyi.md"
  }
]