[
  {
    "name": "001_Little-Prince",
    "file": "001_Little-Prince.md"
  },
  {
    "name": "002_Haoe'smaomaochong",
    "file": "002_Haoe'smaomaochong.md"
  },
  {
    "name": "003_xl'swang",
    "file": "003_xl'swang.md"
  },
  {
    "name": "004_caicaiwoyoudaini",
    "file": "004_caicaiwoyoudaini.md"
  },
  {
    "name": "005_yeshouCountry",
    "file": "005_yeshouCountry.md"
  },
  {
    "name": "006_xzhupqSeries",
    "file": "006_xzhupqSeries.md"
  },
  {
    "name": "007_ailisimengyouxianjing",
    "file": "007_ailisimengyouxianjing.md"
  },
  {
    "name": "008_bu1yang'sKamLa",
    "file": "008_bu1yang'sKamLa.md"
  },
  {
    "name": "009_liulfengsheng",
    "file": "009_liulfengsheng.md"
  },
  {
    "name": "010_bnxiongqingjingEducationhuib",
    "file": "010_bnxiongqingjingEducationhuib.md"
  },
  {
    "name": "011_huole100wanci'smao",
    "file": "011_huole100wanci'smao.md"
  },
  {
    "name": "012_Peter·pan",
    "file": "012_Peter·pan.md"
  },
  {
    "name": "013_chuangbian'sxdoudou",
    "file": "013_chuangbian'sxdoudou.md"
  },
  {
    "name": "014_caofangzi",
    "file": "014_caofangzi.md"
  },
  {
    "name": "015_Nielsqielvxingji",
    "file": "015_Nielsqielvxingji.md"
  },
  {
    "name": "016_shuihaizi",
    "file": "016_shuihaizi.md"
  },
  {
    "name": "017_huapopo",
    "file": "017_huapopo.md"
  },
  {
    "name": "018_yeye1dingyoubanf",
    "file": "018_yeye1dingyoubanf.md"
  },
  {
    "name": "019_ffshengqile",
    "file": "019_ffshengqile.md"
  },
  {
    "name": "020_LvMountainqiang'sAnni",
    "file": "020_LvMountainqiang'sAnni.md"
  },
  {
    "name": "021_chaliheqiaoKeligongchang",
    "file": "021_chaliheqiaoKeligongchang.md"
  },
  {
    "name": "022_xxiongbaobaoSeries",
    "file": "022_xxiongbaobaoSeries.md"
  },
  {
    "name": "023_qiuyin'sDiary",
    "file": "023_qiuyin'sDiary.md"
  },
  {
    "name": "024_San-Maoliulangji",
    "file": "024_San-Maoliulangji.md"
  },
  {
    "name": "025_DaZhonghxunbaoSeries",
    "file": "025_DaZhonghxunbaoSeries.md"
  },
  {
    "name": "026_NanyLegendary",
    "file": "026_NanyLegendary.md"
  },
  {
    "name": "027_taojxtu",
    "file": "027_taojxtu.md"
  },
  {
    "name": "028_meitnaohebuGaoxing",
    "file": "028_meitnaohebuGaoxing.md"
  },
  {
    "name": "029_caihongse'shua",
    "file": "029_caihongse'shua.md"
  },
  {
    "name": "030_qingTongkuihua",
    "file": "030_qingTongkuihua.md"
  },
  {
    "name": "031_chuixNo'ste",
    "file": "031_chuixNo'ste.md"
  },
  {
    "name": "032_xiaomaoDiary",
    "file": "032_xiaomaoDiary.md"
  },
  {
    "name": "033_Haoe'sxshe",
    "file": "033_Haoe'sxshe.md"
  },
  {
    "name": "034_fuyuzi",
    "file": "034_fuyuzi.md"
  },
  {
    "name": "035_sqxiaocSeries",
    "file": "035_sqxiaocSeries.md"
  },
  {
    "name": "036_Changwazipp",
    "file": "036_Changwazipp.md"
  },
  {
    "name": "037_SeadiliangwanLi",
    "file": "037_SeadiliangwanLi.md"
  },
  {
    "name": "038_Lvyexianzong",
    "file": "038_Lvyexianzong.md"
  },
  {
    "name": "039_pplzongdongyuan",
    "file": "039_pplzongdongyuan.md"
  },
  {
    "name": "040_MonthLiang'sweid",
    "file": "040_MonthLiang'sweid.md"
  },
  {
    "name": "041_Afanti'sStory",
    "file": "041_Afanti'sStory.md"
  },
  {
    "name": "042_810thuanyoudqiu",
    "file": "042_810thuanyoudqiu.md"
  },
  {
    "name": "043_benlang'sStory",
    "file": "043_benlang'sStory.md"
  },
  {
    "name": "044_nanshengjiaLiquanc",
    "file": "044_nanshengjiaLiquanc.md"
  },
  {
    "name": "045_ddlxianji",
    "file": "045_ddlxianji.md"
  },
  {
    "name": "046_sbimliang",
    "file": "046_sbimliang.md"
  },
  {
    "name": "047_xpihaiDiarySeries",
    "file": "047_xpihaiDiarySeries.md"
  },
  {
    "name": "048_daocaop",
    "file": "048_daocaop.md"
  },
  {
    "name": "049_PalacexdyekonglongSeries",
    "file": "049_PalacexdyekonglongSeries.md"
  },
  {
    "name": "050_YisoFable",
    "file": "050_YisoFable.md"
  },
  {
    "name": "051_GreenFairy-Tale",
    "file": "051_GreenFairy-Tale.md"
  },
  {
    "name": "052_AntushengFairy-Tale",
    "file": "052_AntushengFairy-Tale.md"
  },
  {
    "name": "053_xbtqyuji",
    "file": "053_xbtqyuji.md"
  },
  {
    "name": "054_Tomsoylxianji",
    "file": "054_Tomsoylxianji.md"
  },
  {
    "name": "055_shiluo's1jiao",
    "file": "055_shiluo's1jiao.md"
  },
  {
    "name": "056_aixinshu",
    "file": "056_aixinshu.md"
  },
  {
    "name": "057_bbxiongSeries",
    "file": "057_bbxiongSeries.md"
  },
  {
    "name": "058_Three-BodyShaoYearEdition",
    "file": "058_Three-BodyShaoYearEdition.md"
  },
  {
    "name": "059_MountainSeaj",
    "file": "059_MountainSeaj.md"
  },
  {
    "name": "060_yachiDajieXinxianshi",
    "file": "060_yachiDajieXinxianshi.md"
  },
  {
    "name": "061_lbinXunpiaoliuji",
    "file": "061_lbinXunpiaoliuji.md"
  },
  {
    "name": "062_hulRiverc",
    "file": "062_hulRiverc.md"
  },
  {
    "name": "063_xzhupqDaFilmSeries",
    "file": "063_xzhupqDaFilmSeries.md"
  },
  {
    "name": "064_10wangeweishme",
    "file": "064_10wangeweishme.md"
  },
  {
    "name": "065_yangcongtlxianji",
    "file": "065_yangcongtlxianji.md"
  },
  {
    "name": "066_wobaba",
    "file": "066_wobaba.md"
  },
  {
    "name": "067_womama",
    "file": "067_womama.md"
  },
  {
    "name": "068_lnhu'sStory",
    "file": "068_lnhu'sStory.md"
  },
  {
    "name": "069_Humanqiyuan'sStory",
    "file": "069_Humanqiyuan'sStory.md"
  },
  {
    "name": "070_huamul",
    "file": "070_huamul.md"
  },
  {
    "name": "071_Little-PrincelitisEdition",
    "file": "071_Little-PrincelitisEdition.md"
  },
  {
    "name": "072_xdAnimalStoryji",
    "file": "072_xdAnimalStoryji.md"
  },
  {
    "name": "073_GreeceMythStory",
    "file": "073_GreeceMythStory.md"
  },
  {
    "name": "074_Adai'ssjie",
    "file": "074_Adai'ssjie.md"
  },
  {
    "name": "075_xfeixiaPeterpanhuibEdition",
    "file": "075_xfeixiaPeterpanhuibEdition.md"
  },
  {
    "name": "076_duziLi'sxhuoc",
    "file": "076_duziLi'sxhuoc.md"
  },
  {
    "name": "077_meitnaohebuGaoxingpinyinEdition",
    "file": "077_meitnaohebuGaoxingpinyinEdition.md"
  },
  {
    "name": "078_chengyuStory",
    "file": "078_chengyuStory.md"
  },
  {
    "name": "079_Suf'ssjie",
    "file": "079_Suf'ssjie.md"
  },
  {
    "name": "080_LvyexianzonghuibEdition",
    "file": "080_LvyexianzonghuibEdition.md"
  },
  {
    "name": "081_CitynJiushi",
    "file": "081_CitynJiushi.md"
  },
  {
    "name": "082_xiegeiertong'sChinaHistory",
    "file": "082_xiegeiertong'sChinaHistory.md"
  },
  {
    "name": "083_chuixNo'stepinyinEdition",
    "file": "083_chuixNo'stepinyinEdition.md"
  },
  {
    "name": "084_DajiaoyatiaoBallet",
    "file": "084_DajiaoyatiaoBallet.md"
  },
  {
    "name": "085_hlerjiangsjieshi",
    "file": "085_hlerjiangsjieshi.md"
  },
  {
    "name": "086_bukesiyi'slvcheng",
    "file": "086_bukesiyi'slvcheng.md"
  },
  {
    "name": "087_jiahuaCountrylxianji",
    "file": "087_jiahuaCountrylxianji.md"
  },
  {
    "name": "088_xiegeiertong'ssjieHistory",
    "file": "088_xiegeiertong'ssjieHistory.md"
  },
  {
    "name": "089_doukouTown'sjuminheqiangdao",
    "file": "089_doukouTown'sjuminheqiangdao.md"
  },
  {
    "name": "090_liulfengshengpinyinEdition",
    "file": "090_liulfengshengpinyinEdition.md"
  },
  {
    "name": "091_NielsqielvxingjichatEdition",
    "file": "091_NielsqielvxingjichatEdition.md"
  },
  {
    "name": "092_SeadiliangwanLiqingShaoEdition",
    "file": "092_SeadiliangwanLiqingShaoEdition.md"
  },
  {
    "name": "093_glfyouji",
    "file": "093_glfyouji.md"
  },
  {
    "name": "094_muouqyuji",
    "file": "094_muouqyuji.md"
  },
  {
    "name": "095_fanerNaKehuanClassictaozhuang",
    "file": "095_fanerNaKehuanClassictaozhuang.md"
  },
  {
    "name": "096_wo'sqingxuxguaishou",
    "file": "096_wo'sqingxuxguaishou.md"
  },
  {
    "name": "097_kongziAnalectsStory",
    "file": "097_kongziAnalectsStory.md"
  },
  {
    "name": "098_xzhupqwoaiDaziran",
    "file": "098_xzhupqwoaiDaziran.md"
  },
  {
    "name": "099_ChinaMythStory",
    "file": "099_ChinaMythStory.md"
  },
  {
    "name": "100_DaZhonghxunbaojiSeries",
    "file": "100_DaZhonghxunbaojiSeries.md"
  },
  {
    "name": "index",
    "file": "index.md"
  }
]